MANIFEST.in
README.md
setup.py
beniutils/__init__.py
beniutils/aio.py
beniutils/btask.py
beniutils/byte.py
beniutils/cmd.py
beniutils/execute.py
beniutils/http.py
beniutils/log.py
beniutils/print.py
beniutils/task.py
beniutils/zip.py
beniutils.egg-info/PKG-INFO
beniutils.egg-info/SOURCES.txt
beniutils.egg-info/dependency_links.txt
beniutils.egg-info/entry_points.txt
beniutils.egg-info/requires.txt
beniutils.egg-info/top_level.txt
beniutils/data/task_build.zip
beniutils/data/task_create.zip
test/__init__.py
test/conftest.py
test/test_template.py