Metadata-Version: 2.1
Name: beniutils
Version: 0.0.121
Summary: utils library for Beni
Home-page: https://pypi.org/project/beniutils/
Author: Beni
Author-email: benimang@126.com
License: MIT License
Keywords: beni
Platform: any
